tradex/__init__.py
tradex/constants/__init__.py
tradex/constants/enuming.py
tradex/constants/listting.py
tradex/models/__init__.py
tradex/models/order.py
tradex/models/take_profit.py
tradex/providers/__init__.py
tradex/providers/binance/__init__.py
tradex/providers/binance/info/__init__.py
tradex/providers/binance/info/enterpoints.py
tradex/providers/binance/order/__init__.py
tradex/utils/__init__.py
tradex/utils/derivative.py
tradex/utils/fibonacci.py
tradex/utils/margin.py
tradex/utils/profit.py
tradex/utils/size.py
pytradex-0.3.1.dist-info/METADATA
pytradex-0.3.1.dist-info/WHEEL
pytradex-0.3.1.dist-info/RECORD
