Metadata-Version: 2.4
Name: pytradex
Version: 0.3.1
Summary: Trading system for cryptocurrency exchange.
Project-URL: Documentation, https://github.com/zhongjiajie/tradex#readme
Project-URL: Issues, https://github.com/zhongjiajie/tradex/issues
Project-URL: Source, https://github.com/zhongjiajie/tradex
Author-email: Jay Chung <zhongjiajie955@gmail.com>
License-Expression: MIT
Keywords: crypto,cryptocurrency,trade
Classifier: Development Status :: 1 - Planning
Classifier: Intended Audience :: Developers
Classifier: Operating System :: Microsoft :: Windows
Classifier: Operating System :: POSIX
Classifier: Operating System :: Unix
Classifier: Programming Language :: Python
Classifier: Programming Language :: Python :: 3.8
Classifier: Programming Language :: Python :: 3.9
Classifier: Programming Language :: Python :: 3.10
Classifier: Programming Language :: Python :: 3.11
Classifier: Programming Language :: Python :: 3.12
Classifier: Programming Language :: Python :: Implementation :: CPython
Classifier: Programming Language :: Python :: Implementation :: PyPy
Classifier: Topic :: Software Development :: User Interfaces
Requires-Python: >=3.10
